openCFR/InfoSet.py
openCFR/LICENSE.txt
openCFR/README.md
openCFR/Trainer.py
openCFR/__init__.py
openCFR/games/Game.py
openCFR/games/GameNode.py
openCFR/games/UtilityNode.py
openCFR/games/__init__.py
openCFR/games/sample_games/Kuhn.py
openCFR/games/sample_games/RPS.py
openCFR/games/sample_games/TexasHoldEm.py
openCFR/games/sample_games/__init__.py
openCFR/minimizers/CFRPlus.py
openCFR/minimizers/MCCFR_External.py
openCFR/minimizers/MCCFR_Outcome.py
openCFR/minimizers/RBP_CFR.py
openCFR/minimizers/VanillaCFR.py
openCFR/minimizers/__init__.py
openCFR/pretrained/Kuhn_final.pickle
openCFR/pretrained/RPS_final.pickle
openCFR/pretrained/TexasHoldEm_final.pickle
openCFR-1.0.0.dist-info/LICENSE.txt
openCFR-1.0.0.dist-info/METADATA
openCFR-1.0.0.dist-info/WHEEL
openCFR-1.0.0.dist-info/top_level.txt
openCFR-1.0.0.dist-info/RECORD
